kmean/__init__.py
KmeanBestK-0.0.12.dist-info/LICENSE.txt
KmeanBestK-0.0.12.dist-info/METADATA
KmeanBestK-0.0.12.dist-info/WHEEL
KmeanBestK-0.0.12.dist-info/top_level.txt
KmeanBestK-0.0.12.dist-info/RECORD
